LICENSE
MANIFEST.in
README.md
pyproject.toml
setup.py
gcdevproxy/__init__.py
gcdevproxy/aio.py
gcdevproxy/http.py
gcdevproxy/native.py
gcdevproxy/proxy.py
gcdevproxy.egg-info/PKG-INFO
gcdevproxy.egg-info/SOURCES.txt
gcdevproxy.egg-info/dependency_links.txt
gcdevproxy.egg-info/top_level.txt
native/.git
native/.gitignore
native/CHANGELOG.md
native/Cargo.lock
native/Cargo.toml
native/LICENSE
native/README.md
native/examples/example.rs
native/include/gcproxy.h
native/src/auth.rs
native/src/binding.rs
native/src/body.rs
native/src/device.rs
native/src/error.rs
native/src/lib.rs
native/src/response.rs
native/src/shutdown.rs
native/src/tls.rs
native/src/utils.rs
native/src/acme/challenge.rs
native/src/acme/client.rs
native/src/acme/jws.rs
native/src/acme/mod.rs
native/src/acme/utils.rs
native/src/acme/watchdog.rs
native/src/exports/log.rs
native/src/exports/macros.rs
native/src/exports/mod.rs
native/src/exports/proxy.rs
native/src/exports/request.rs
native/src/exports/response.rs