Metadata-Version: 2.1
Name: gcdevproxy
Version: 0.1.10
Summary: GoodCam Device Proxy lib
Author-email: GoodCam <dev@goodcam.io>
Project-URL: Homepage, https://github.com/GoodCam/device-proxy-lib-python
Classifier: Programming Language :: Python :: 3
Requires-Python: >=3.7
License-File: LICENSE
